csvinspector/__init__.py
csvinspector/__main__.py
csvinspector/inspector.py
csvinspector/report_generator.py
csvinspector/utils.py
csvinspector/visualizer.py
csvinspector-0.1.1.dist-info/METADATA
csvinspector-0.1.1.dist-info/WHEEL
csvinspector-0.1.1.dist-info/top_level.txt
csvinspector-0.1.1.dist-info/RECORD
