Metadata-Version: 2.4
Name: csvinspector
Version: 0.1.1
Summary: A simple library for preprocessing and EDA on CSV files
Home-page: https://github.com/abhii14758/csvinspector
Author: Abhi Bhimani
Author-email: abhibhimani14758@gmail.com
Classifier: Programming Language :: Python :: 3
Classifier: License :: OSI Approved :: MIT License
Classifier: Operating System :: OS Independent
Requires-Python: >=3.7
Requires-Dist: pandas>=1.3.0
Requires-Dist: matplotlib>=3.4.0
Requires-Dist: seaborn>=0.11.0
Requires-Dist: missingno>=0.5.0
Requires-Dist: numpy>=1.21.0
Dynamic: author
Dynamic: author-email
Dynamic: classifier
Dynamic: description
Dynamic: description-content-type
Dynamic: home-page
Dynamic: requires-dist
Dynamic: requires-python
Dynamic: summary
